royman_tools/__init__.py
royman_tools/project_creator.py
royman_tools/tcp.py
royman_tools/web.py
royman_tools-0.0.3.dist-info/LICENSE
royman_tools-0.0.3.dist-info/METADATA
royman_tools-0.0.3.dist-info/WHEEL
royman_tools-0.0.3.dist-info/entry_points.txt
royman_tools-0.0.3.dist-info/top_level.txt
royman_tools-0.0.3.dist-info/RECORD
