Metadata-Version: 2.1
Name: royman-tools
Version: 0.0.3
Summary: A collection of tools
Home-page: https://github.com/roymanigley/royman-tools
Author: Roy Manigley
Author-email: roy.manigley@gmail.com
License: MIT
Classifier: Development Status :: 1 - Planning
Classifier: Intended Audience :: Science/Research
Classifier: License :: OSI Approved :: MIT License
Classifier: Operating System :: POSIX :: Linux
Classifier: Programming Language :: Python :: 3.10
License-File: LICENSE
Requires-Dist: click (>=8.1.3)
Requires-Dist: requests (==2.31.0)
